{
    "/js/app.js": "/js/app.js?id=865ede9f9376c8644485",
    "/css/app.css": "/css/app.css?id=49474520e28920826958",
    "/js/components/about.db959993fbd4e9d73433.js": "/js/components/about.db959993fbd4e9d73433.js?id=38ae712524e387b5a6b7",
    "/js/components/help.ce27cf0e57896042aeae.js": "/js/components/help.ce27cf0e57896042aeae.js?id=2079a87e6ec18c31638d",
    "/js/components/index.ee7c6ec48b13c93a7864.js": "/js/components/index.ee7c6ec48b13c93a7864.js?id=7c9ffc4a87aafe0e4a2a",
    "/js/components/login.8aa4510a77d75ec3d012.js": "/js/components/login.8aa4510a77d75ec3d012.js?id=365203db1bb361380def",
    "/js/components/post.ea3a2fb37072165ab2ef.js": "/js/components/post.ea3a2fb37072165ab2ef.js?id=5880656e353ac65cbcf0",
    "/js/components/posts.f6254d82cbc6dcb2c16f.js": "/js/components/posts.f6254d82cbc6dcb2c16f.js?id=ce82969daac701cce838",
    "/js/components/profile.2db4893d70ab2c558be7.js": "/js/components/profile.2db4893d70ab2c558be7.js?id=1cde1dd109000b45190a",
    "/js/components/register.625a0008d4a06105666f.js": "/js/components/register.625a0008d4a06105666f.js?id=f880c0572e71f9f13a0a",
    "/js/components/settings.6017b3bb2f457af3e510.js": "/js/components/settings.6017b3bb2f457af3e510.js?id=6a54659d6bf41bc8ad98"
}
